vercel_kv_sdk.py
vercel_kv_sdk-0.1.2.dist-info/LICENSE
vercel_kv_sdk-0.1.2.dist-info/METADATA
vercel_kv_sdk-0.1.2.dist-info/WHEEL
vercel_kv_sdk-0.1.2.dist-info/top_level.txt
vercel_kv_sdk-0.1.2.dist-info/RECORD
