Metadata-Version: 2.1
Name: vercel-kv-sdk
Version: 0.1.2
Summary: https://vercel.com/docs/storage/vercel-kv/rest-api
Home-page: https://github.com/LidamaoHub/vercel-kv-sdk
Author: Lidamao
License: MIT
Platform: UNKNOWN
Classifier: License :: OSI Approved :: MIT License
Classifier: Programming Language :: Python :: 3.6
Classifier: Programming Language :: Python :: 3.7
Classifier: Programming Language :: Python :: 3.8
Classifier: Programming Language :: Python :: 3.9
Requires-Dist: python-dotenv (>=0.21.1)
Requires-Dist: requests
Requires-Dist: pydantic (>=1.10.11)
Provides-Extra: dev
Requires-Dist: pytest ; extra == 'dev'
Requires-Dist: tox ; extra == 'dev'
